words_tui/__about__.py
words_tui/__init__.py
words_tui/__main__.py
words_tui/cli/__init__.py
words_tui/tui/__init__.py
words_tui/tui/app.css
words_tui/tui/app.py
words_tui/tui/db.py
words_tui/tui/settings.css
words_tui/tui/text_editor.py
words_tui-23.6.dist-info/METADATA
words_tui-23.6.dist-info/WHEEL
words_tui-23.6.dist-info/entry_points.txt
words_tui-23.6.dist-info/licenses/LICENSE.txt
words_tui-23.6.dist-info/RECORD
