Metadata-Version: 2.1
Name: words-tui
Version: 23.6
Summary: A TUI (Text User Interface) app for daily writing.
Project-URL: Documentation, https://github.com/anze3db/words-tui#readme
Project-URL: Issues, https://github.com/anze3db/words-tui/issues
Project-URL: Source, https://github.com/anze3db/words-tui
Project-URL: Changelog, https://github.com/anze3db/words-tui/blob/main/CHANGELOG.md
Author-email: Anže Pečar <anze@pecar.me>
License-Expression: MIT
License-File: LICENSE.txt
Classifier: Development Status :: 4 - Beta
Classifier: Programming Language :: Python
Classifier: Programming Language :: Python :: 3.8
Classifier: Programming Language :: Python :: 3.9
Classifier: Programming Language :: Python :: 3.10
Classifier: Programming Language :: Python :: 3.11
Classifier: Programming Language :: Python :: 3.12
Classifier: Programming Language :: Python :: Implementation :: CPython
Classifier: Programming Language :: Python :: Implementation :: PyPy
Requires-Python: >=3.8
Requires-Dist: click
Requires-Dist: peewee
Requires-Dist: textual
Requires-Dist: tree-sitter
